care/__init__.py
care/constants.py
care/logo.txt
care/adsorption/__init__.py
care/adsorption/dockonsurf/__init__.py
care/adsorption/dockonsurf/dockonsurf.py
care/adsorption/dockonsurf/setup.py
care/adsorption/dockonsurf/src/__init__.py
care/adsorption/dockonsurf/src/dockonsurf/ASANN.py
care/adsorption/dockonsurf/src/dockonsurf/__init__.py
care/adsorption/dockonsurf/src/dockonsurf/dos_input.py
care/adsorption/dockonsurf/src/dockonsurf/formats.py
care/adsorption/dockonsurf/src/dockonsurf/internal_rotate.py
care/adsorption/dockonsurf/src/dockonsurf/screening.py
care/adsorption/dockonsurf/src/dockonsurf/utilities.py
care/crn/__init__.py
care/crn/elementary_reaction.py
care/crn/filters.py
care/crn/graph.py
care/crn/intermediate.py
care/crn/network_reduction.py
care/crn/reaction_network.py
care/crn/surface.py
care/crn/visualize.py
care/crn/templates/__init__.py
care/crn/templates/adsorption.py
care/crn/templates/chemspace.py
care/crn/templates/dissociation.py
care/crn/templates/eley_rideal.py
care/crn/templates/pcet.py
care/crn/templates/rearrengement.py
care/crn/utils/__init__.py
care/crn/utils/blueprint.py
care/crn/utils/electro.py
care/crn/utils/species.py
care/data/metal_surfaces.db
care/evaluators/__init__.py
care/evaluators/energy_estimator.py
care/evaluators/reaction_estimators.py
care/evaluators/utils.py
care/evaluators/gamenet_uq/__init__.py
care/evaluators/gamenet_uq/functions.py
care/evaluators/gamenet_uq/graph.py
care/evaluators/gamenet_uq/graph_filters.py
care/evaluators/gamenet_uq/graph_tools.py
care/evaluators/gamenet_uq/interface.py
care/evaluators/gamenet_uq/nets.py
care/evaluators/gamenet_uq/node_featurizers.py
care/evaluators/gamenet_uq/model/GNN.pth
care/evaluators/gamenet_uq/model/device.txt
care/evaluators/gamenet_uq/model/input.txt
care/evaluators/gamenet_uq/model/one_hot_encoder_elements.pth
care/evaluators/gamenet_uq/model/performance.txt
care/evaluators/mace/__init__.py
care/evaluators/mace/interface.py
care/evaluators/ocp/__init__.py
care_crn-0.3.0.dist-info/licenses/LICENSE
care_crn-0.3.0.dist-info/METADATA
care_crn-0.3.0.dist-info/WHEEL
care_crn-0.3.0.dist-info/entry_points.txt
care_crn-0.3.0.dist-info/top_level.txt
care_crn-0.3.0.dist-info/RECORD
