Metadata-Version: 2.4
Name: care-crn
Version: 0.3.0
Summary: Chemical Reaction Network generator for heterogenous catalysis
Author-email: Santiago Morandi <santiagomorandi@yahoo.it>, Oliver Loveday <oliverlovros@gmail.com>, Pol Sanz Berman <psanz@iciq.es>
Maintainer-email: Santiago Morandi <santiagomorandi@yahoo.it>, Oliver Loveday <oliverlovros@gmail.com>, Pol Sanz Berman <psanz@iciq.es>
License: MIT License
Project-URL: Repository, https://github.com/LopezGroup-ICIQ/care
Project-URL: Bugtracker, https://github.com/LopezGroup-ICIQ/care/issues
Keywords: heterogeneous catalysis,chemical reaction networks,kinetics,machine learning
Classifier: Development Status :: 4 - Beta
Classifier: Programming Language :: Python :: 3.12
Requires-Python: ==3.12.*
License-File: LICENSE
Requires-Dist: acat==1.6.8
Requires-Dist: ase==3.24.0
Requires-Dist: matplotlib==3.8.0
Requires-Dist: networkx==3.2
Requires-Dist: numpy==1.26.4
Requires-Dist: pandas==2.2.0
Requires-Dist: prettytable==3.9.0
Requires-Dist: pydot==2.0.0
Requires-Dist: mp-api==0.45.3
Requires-Dist: pymatgen
Requires-Dist: torch==2.4.0
Requires-Dist: torch_geometric==2.5.3
Requires-Dist: rdkit==2023.9.6
Requires-Dist: scikit_learn==1.5.1
Requires-Dist: scipy==1.15.1
Requires-Dist: numba
Requires-Dist: energydiagram
Requires-Dist: rich
Requires-Dist: py-cpuinfo
Requires-Dist: psutil
Requires-Dist: dask[complete]==2025.3.0
Requires-Dist: juliacall==0.9.27
Requires-Dist: openpyxl==3.1.5
Provides-Extra: ocp
Requires-Dist: fairchem-core==1.4.0; extra == "ocp"
Provides-Extra: mace
Requires-Dist: mace-torch==0.3.12; extra == "mace"
Requires-Dist: torch-dftd==0.5.1; extra == "mace"
Provides-Extra: petmad
Requires-Dist: pet_mad==1.4.3; extra == "petmad"
Provides-Extra: orb
Requires-Dist: orb-models==0.4.2; extra == "orb"
Requires-Dist: pynanoflann==0.10.0; extra == "orb"
Provides-Extra: sevennet
Requires-Dist: sevenn==0.11.2; extra == "sevennet"
Provides-Extra: dev
Requires-Dist: pytest; extra == "dev"
Requires-Dist: pytest-cov; extra == "dev"
Requires-Dist: coverage; extra == "dev"
Requires-Dist: codecov; extra == "dev"
Requires-Dist: flake8; extra == "dev"
Dynamic: license-file
